cookiecutter.json
hooks/post_gen_project.py
hooks/pre_gen_project.py
ppwjb/cli.py
{{cookiecutter.project_slug}}/.coveragerc
{{cookiecutter.project_slug}}/.editorconfig
{{cookiecutter.project_slug}}/.flake8
{{cookiecutter.project_slug}}/.github/ISSUE_TEMPLATE.md
{{cookiecutter.project_slug}}/.github/workflows/dev.yml
{{cookiecutter.project_slug}}/.github/workflows/release.yml
{{cookiecutter.project_slug}}/.gitignore
{{cookiecutter.project_slug}}/.isort.cfg
{{cookiecutter.project_slug}}/.pre-commit-config.yaml
{{cookiecutter.project_slug}}/LICENSE
{{cookiecutter.project_slug}}/Makefile
{{cookiecutter.project_slug}}/README.md
{{cookiecutter.project_slug}}/book/_config.yml
{{cookiecutter.project_slug}}/book/_toc.yml
{{cookiecutter.project_slug}}/book/api.rst
{{cookiecutter.project_slug}}/book/authoring.md
{{cookiecutter.project_slug}}/book/authors.md
{{cookiecutter.project_slug}}/book/contributing.md
{{cookiecutter.project_slug}}/book/history.md
{{cookiecutter.project_slug}}/book/index.md
{{cookiecutter.project_slug}}/book/installation.md
{{cookiecutter.project_slug}}/book/logo.svg
{{cookiecutter.project_slug}}/book/notebook.ipynb
{{cookiecutter.project_slug}}/book/references.bib
{{cookiecutter.project_slug}}/book/usage.md
{{cookiecutter.project_slug}}/pyproject.toml
{{cookiecutter.project_slug}}/pyrightconfig.json
{{cookiecutter.project_slug}}/tests/__init__.py
{{cookiecutter.project_slug}}/tests/test_{{cookiecutter.project_slug}}.py
{{cookiecutter.project_slug}}/tox.ini
{{cookiecutter.project_slug}}/{{cookiecutter.project_slug}}/__init__.py
{{cookiecutter.project_slug}}/{{cookiecutter.project_slug}}/cli.py
{{cookiecutter.project_slug}}/{{cookiecutter.project_slug}}/{{cookiecutter.project_slug}}.py
ppwjb-0.0.3.dist-info/entry_points.txt
ppwjb-0.0.3.dist-info/LICENSE
ppwjb-0.0.3.dist-info/WHEEL
ppwjb-0.0.3.dist-info/METADATA
ppwjb-0.0.3.dist-info/RECORD
