Metadata-Version: 2.1
Name: ppwjb
Version: 0.0.3
Summary: Python project wizard with Jupyter Book
Home-page: https://github.com/ondraz/cookiecutter-pypackage-jupyter-book
License: BSD-3-Clause
Keywords: cookiecutter,template,package
Author: Ondra Zahradnik
Author-email: ondra.zahradnik@gmail.com
Requires-Python: >=3.7,<3.11
Classifier: License :: OSI Approved :: BSD License
Classifier: Programming Language :: Python :: 3
Classifier: Programming Language :: Python :: 3.10
Classifier: Programming Language :: Python :: 3.7
Classifier: Programming Language :: Python :: 3.8
Classifier: Programming Language :: Python :: 3.9
Provides-Extra: dev
Requires-Dist: cookiecutter (==1.7.2)
Requires-Dist: fire (>=0.4.0,<0.5.0); extra == "dev"
Requires-Dist: jupyter-book (>=0.12.2,<0.13.0); extra == "dev"
Requires-Dist: pytest (>=5.4.3,<6.0.0); extra == "dev"
Requires-Dist: pytest-cookies (>=0.5.1,<0.6.0); extra == "dev"
Requires-Dist: pytest-cov (>=2.10.1,<3.0.0); extra == "dev"
Requires-Dist: pyyaml (>=5.3.1,<6.0.0); extra == "dev"
Requires-Dist: tox (>=3.20.1,<4.0.0); extra == "dev"
Project-URL: Documentation, https://ondraz.github.io/cookiecutter-pypackage-jupyter-book/
Project-URL: Repository, https://github.com/ondraz/cookiecutter-pypackage-jupyter-book
